[
	{
		"platform": "Steam",
		"timestamp": 1773686510000,
		"game": "Phasmophobia",
		"webpage": "https://store.steampowered.com/app/739630",
		"icon": "https://steamcdn-a.akamaihd.net/steamcommunity/public/images/apps/739630/18723e066c3829fb9d98d5bfbbccd3b081dd14e3.jpg",
		"title": "Cash Cow",
		"description": "Spend $50,000",
		"url": "https://steamcommunity.com/stats/739630/achievements",
		"$type": "SteamAchievementActivity"
	},
	{
		"platform": "Steam",
		"timestamp": 1773688606000,
		"game": "Phasmophobia",
		"webpage": "https://store.steampowered.com/app/739630",
		"icon": "https://steamcdn-a.akamaihd.net/steamcommunity/public/images/apps/739630/61ac93deec410268a0c56d028d2a514ad9df659d.jpg",
		"title": "Obake Discovered",
		"description": "Successfully identify your first Obake and survive",
		"url": "https://steamcommunity.com/stats/739630/achievements",
		"$type": "SteamAchievementActivity"
	},
	{
		"platform": "GitHub",
		"timestamp": 1773750453000,
		"username": "eccs0103",
		"url": "https://github.com/eccs0103/adaptive-extender",
		"repository": "adaptive-extender",
		"sha": "ac0ea1b5b200a529ebe14a0b65f0cf99dd060281",
		"$type": "GitHubPushActivity"
	},
	{
		"platform": "GitHub",
		"timestamp": 1773750456000,
		"username": "eccs0103",
		"url": "https://github.com/eccs0103/adaptive-extender",
		"repository": "adaptive-extender",
		"sha": "b2fd8b84810c479a98a9f7212533d3822d6ab5bf",
		"$type": "GitHubPushActivity"
	},
	{
		"platform": "GitHub",
		"timestamp": 1773750458000,
		"username": "eccs0103",
		"url": "https://github.com/eccs0103/adaptive-extender",
		"repository": "adaptive-extender",
		"sha": "426f0b4d3d43e6cdc0eb15bf28b5675f8d5134d3",
		"$type": "GitHubPushActivity"
	},
	{
		"platform": "GitHub",
		"timestamp": 1773750461000,
		"username": "eccs0103",
		"url": "https://github.com/eccs0103/adaptive-extender",
		"repository": "adaptive-extender",
		"sha": "5087bd0f34d90f57f518f82cc4d8abcdd6db0e3b",
		"$type": "GitHubPushActivity"
	},
	{
		"platform": "GitHub",
		"timestamp": 1773750969000,
		"username": "eccs0103",
		"url": "https://github.com/eccs0103/adaptive-extender",
		"repository": "adaptive-extender",
		"sha": "9c9885cfee51f9b8828b9e515c97950b22e9777f",
		"$type": "GitHubPushActivity"
	},
	{
		"platform": "GitHub",
		"timestamp": 1773751791000,
		"username": "eccs0103",
		"url": "https://github.com/eccs0103/adaptive-extender",
		"repository": "adaptive-extender",
		"sha": "ac4e7eca7284267f542165b0c7b511b6f2dc24f6",
		"$type": "GitHubPushActivity"
	},
	{
		"platform": "GitHub",
		"timestamp": 1773754825000,
		"username": "eccs0103",
		"url": "https://github.com/eccs0103/eccs0103.github.io",
		"repository": "eccs0103.github.io",
		"sha": "9b7503959a2880e64b0d615a5fd01d33284707f2",
		"$type": "GitHubPushActivity"
	},
	{
		"platform": "GitHub",
		"timestamp": 1773754827000,
		"username": "eccs0103",
		"url": "https://github.com/eccs0103/eccs0103.github.io",
		"repository": "eccs0103.github.io",
		"sha": "22214bd5518f2e9b2bf4d081f82ef05371ecd4e0",
		"$type": "GitHubPushActivity"
	},
	{
		"platform": "GitHub",
		"timestamp": 1773768684000,
		"username": "eccs0103",
		"url": "https://github.com/eccs0103/adaptive-extender",
		"repository": "adaptive-extender",
		"name": "v0.9.10",
		"$type": "GitHubDeleteTagActivity"
	},
	{
		"platform": "GitHub",
		"timestamp": 1773769249000,
		"username": "eccs0103",
		"url": "https://github.com/eccs0103/adaptive-extender",
		"repository": "adaptive-extender",
		"sha": "3d145b0b48fb3bf7264f8603e5fa80945282d01b",
		"$type": "GitHubPushActivity"
	},
	{
		"platform": "GitHub",
		"timestamp": 1773769251000,
		"username": "eccs0103",
		"url": "https://github.com/eccs0103/adaptive-extender",
		"repository": "adaptive-extender",
		"name": "0.9.10",
		"$type": "GitHubDeleteTagActivity"
	},
	{
		"platform": "GitHub",
		"timestamp": 1773769516000,
		"username": "eccs0103",
		"url": "https://github.com/eccs0103/adaptive-extender",
		"repository": "adaptive-extender",
		"title": "0.9.10",
		"tag_name": "0.9.10",
		"is_prerelease": false,
		"$type": "GitHubReleaseActivity"
	},
	{
		"platform": "GitHub",
		"timestamp": 1773790806000,
		"username": "eccs0103",
		"url": "https://github.com/eccs0103/eccs0103.github.io",
		"repository": "eccs0103.github.io",
		"sha": "ae706a417111014f787977d6ac43ca3b46ed6d31",
		"$type": "GitHubPushActivity"
	},
	{
		"platform": "GitHub",
		"timestamp": 1773790811000,
		"username": "eccs0103",
		"url": "https://github.com/eccs0103/eccs0103.github.io",
		"repository": "eccs0103.github.io",
		"sha": "9782e57ba20f9a31f1a40ba9a4cbdf58b67c8a43",
		"$type": "GitHubPushActivity"
	},
	{
		"platform": "GitHub",
		"timestamp": 1773790815000,
		"username": "eccs0103",
		"url": "https://github.com/eccs0103/eccs0103.github.io",
		"repository": "eccs0103.github.io",
		"sha": "3ba1299fb8c73429e3078330b3a271c6a83d1d9e",
		"$type": "GitHubPushActivity"
	},
	{
		"platform": "GitHub",
		"timestamp": 1773790819000,
		"username": "eccs0103",
		"url": "https://github.com/eccs0103/eccs0103.github.io",
		"repository": "eccs0103.github.io",
		"sha": "b07e97bbef89ae166e7b39f09e26be6d6bd8746f",
		"$type": "GitHubPushActivity"
	},
	{
		"platform": "GitHub",
		"timestamp": 1773791192000,
		"username": "eccs0103",
		"url": "https://github.com/eccs0103/eccs0103.github.io",
		"repository": "eccs0103.github.io",
		"sha": "00d8f44ff33240715167b34e0c008d9710fd220e",
		"$type": "GitHubPushActivity"
	},
	{
		"platform": "GitHub",
		"timestamp": 1773843530000,
		"username": "eccs0103",
		"url": "https://github.com/eccs0103/eccs0103.github.io",
		"repository": "eccs0103.github.io",
		"sha": "7ad76b97d7c7f1c7847a1c120a6fca47b86449a3",
		"$type": "GitHubPushActivity"
	},
	{
		"platform": "GitHub",
		"timestamp": 1773843535000,
		"username": "eccs0103",
		"url": "https://github.com/eccs0103/eccs0103.github.io",
		"repository": "eccs0103.github.io",
		"sha": "5cdf617148fbc768503445a4a52bb70b9b446696",
		"$type": "GitHubPushActivity"
	},
	{
		"platform": "GitHub",
		"timestamp": 1773843538000,
		"username": "eccs0103",
		"url": "https://github.com/eccs0103/eccs0103.github.io",
		"repository": "eccs0103.github.io",
		"sha": "424b864c034e9d2c84651b8f8ef1d347bb1d62fa",
		"$type": "GitHubPushActivity"
	}
]